nyancad/__init__.py
nyancad/anywidget.py
nyancad/api.py
nyancad/netlist.py
nyancad/plot.py
nyancad/schemas.py
nyancad-0.10.3.dist-info/METADATA
nyancad-0.10.3.dist-info/WHEEL
nyancad-0.10.3.dist-info/top_level.txt
nyancad-0.10.3.dist-info/RECORD
