Metadata-Version: 2.4
Name: nyancad
Version: 0.10.3
Summary: NyanCAD Python library for schematic editor with anywidget integration
Author-email: Pepijn de Vos <me@pepijndevos.nl>
License: MPL-2.0
Project-URL: Homepage, https://github.com/NyanCAD/Mosaic
Project-URL: Repository, https://github.com/NyanCAD/Mosaic
Classifier: Development Status :: 3 - Alpha
Classifier: Intended Audience :: Developers
Classifier: License :: OSI Approved :: Mozilla Public License 2.0 (MPL 2.0)
Classifier: Programming Language :: Python :: 3
Classifier: Programming Language :: Python :: 3.8
Classifier: Programming Language :: Python :: 3.9
Classifier: Programming Language :: Python :: 3.10
Classifier: Programming Language :: Python :: 3.11
Classifier: Programming Language :: Python :: 3.12
Requires-Python: >=3.8
Requires-Dist: anywidget>=0.9.0
Requires-Dist: traitlets
Requires-Dist: InSpice
Requires-Dist: holoviews
